{
 "attach_print": 0,
 "channel": "System Notification",
 "condition": "doc.status==\"Open\" or doc.status==\"Working\"",
 "creation": "2021-09-29 14:12:53.983310",
 "date_changed": "exp_end_date",
 "days_in_advance": 1,
 "docstatus": 0,
 "doctype": "Notification",
 "document_type": "Task",
 "enabled": 1,
 "event": "Days Before",
 "idx": 0,
 "is_standard": 1,
 "message": "Add your message here",
 "modified": "2021-10-27 17:04:41.283367",
 "modified_by": "1218408851@qq.com",
 "module": "Projects",
 "name": "\u4efb\u52a1\u5230\u671f\u901a\u77e5",
 "owner": "1218408851@qq.com",
 "recipients": [
  {
   "receiver_by_document_field": "owner",
   "receiver_by_role": "All"
  }
 ],
 "send_system_notification": 0,
 "send_to_all_assignees": 0,
 "subject": "\u4efb\u52a1{{doc.name}}\u5373\u5c06\u7ed3\u675f"
}